languages/__init__.py
languages/data/deepl_languages.json
languages/data/general_languages.json
languages/data/google_languages.json
languages/data/nllb200_languages.json
languages/languages.py
harken_languages-0.1.4.dist-info/METADATA
harken_languages-0.1.4.dist-info/WHEEL
harken_languages-0.1.4.dist-info/RECORD
