Metadata-Version: 2.1
Name: harken-languages
Version: 0.1.4
Summary: ...
Author: Juan Luis García
Author-email: juanluis1702@gmail.com
Requires-Python: >=3
Classifier: Programming Language :: Python :: 3
Classifier: Programming Language :: Python :: 3.4
Classifier: Programming Language :: Python :: 3.5
Classifier: Programming Language :: Python :: 3.6
Classifier: Programming Language :: Python :: 3.7
Classifier: Programming Language :: Python :: 3.8
Classifier: Programming Language :: Python :: 3.9
Classifier: Programming Language :: Python :: 3.10
Classifier: Programming Language :: Python :: 3.11
Classifier: Programming Language :: Python :: 3.12
Requires-Dist: PyICU (>=2.12)
Requires-Dist: funcy (==2.0.0)
Requires-Dist: iso639-lang (==2.2.2)
Requires-Dist: langcodes (==3.3.0)
Requires-Dist: lingua-language-detector (==2.0.2)
Requires-Dist: poetry (==1.7.1)
Requires-Dist: polyglot (==16.7.4)
Requires-Dist: pycld2 (>=0.3)
Requires-Dist: structlog (==23.1.0)
Requires-Dist: wheel (>=0.23.0)
